bas_air_unit_network_dataset/__init__.py
bas_air_unit_network_dataset/exporters/__init __.py
bas_air_unit_network_dataset/exporters/fpl/__init__.py
bas_air_unit_network_dataset/exporters/fpl/fpl.py
bas_air_unit_network_dataset/exporters/fpl/route.py
bas_air_unit_network_dataset/exporters/fpl/route_waypoint.py
bas_air_unit_network_dataset/exporters/fpl/schemas/garmin/FlightPlanv1.xsd
bas_air_unit_network_dataset/exporters/fpl/utils.py
bas_air_unit_network_dataset/exporters/fpl/waypoint.py
bas_air_unit_network_dataset/exporters/report/__init__.py
bas_air_unit_network_dataset/exporters/report/waypoint.py
bas_air_unit_network_dataset/models/__init__.py
bas_air_unit_network_dataset/models/categories.py
bas_air_unit_network_dataset/models/category.py
bas_air_unit_network_dataset/models/network.py
bas_air_unit_network_dataset/models/route.py
bas_air_unit_network_dataset/models/route_waypoint.py
bas_air_unit_network_dataset/models/routes.py
bas_air_unit_network_dataset/models/waypoint.py
bas_air_unit_network_dataset/models/waypoints.py
bas_air_unit_network_dataset/networks/__init__.py
bas_air_unit_network_dataset/networks/bas_air_unit.py
bas_air_unit_network_dataset/resources/templates/air_unit_waypoints.j2
bas_air_unit_network_dataset/resources/templates/air_unit_waypoints_table.j2
bas_air_unit_network_dataset/utils.py
bas_air_unit_network_dataset-0.5.1.dist-info/LICENSE.md
bas_air_unit_network_dataset-0.5.1.dist-info/METADATA
bas_air_unit_network_dataset-0.5.1.dist-info/WHEEL
bas_air_unit_network_dataset-0.5.1.dist-info/RECORD
