Metadata-Version: 2.1
Name: bas-air-unit-network-dataset
Version: 0.5.1
Summary: Utility to process routes and waypoints used by the British Antarctic Survey (BAS) Air Unit
Home-page: https://github.com/antarctica/bas-air-unit-network-dataset
License: MIT
Author: Felix Fennell
Author-email: felnne@bas.ac.uk
Requires-Python: >=3.9,<4.0
Classifier: Intended Audience :: Science/Research
Classifier: License :: OSI Approved :: MIT License
Classifier: Programming Language :: Python :: 3
Classifier: Programming Language :: Python :: 3.9
Classifier: Programming Language :: Python :: 3.10
Classifier: Programming Language :: Python :: 3.11
Classifier: Programming Language :: Python :: 3.12
Requires-Dist: Fiona (>=1.10.1,<2.0.0)
Requires-Dist: Shapely (>=2.0.6,<3.0.0)
Requires-Dist: gpxpy (>=1.6.2,<2.0.0)
Requires-Dist: importlib-resources (>=6.4.5,<7.0.0)
Requires-Dist: jinja2 (>=3.1.4,<4.0.0)
Requires-Dist: lxml (>=5.3,<6.0)
Requires-Dist: python-slugify (>=8.0.4,<9.0.0)
Requires-Dist: ulid-py (>=1.1.0,<2.0.0)
Requires-Dist: weasyprint (>=63.0,<64.0)
Project-URL: Repository, https://github.com/antarctica/bas-air-unit-network-dataset
